bungiesearch/utils.py
bungiesearch/__init__.py
bungiesearch/signals.py
bungiesearch/managers.py
bungiesearch/indices.py
bungiesearch/fields.py
bungiesearch/aliases.py
bungiesearch/management/__init__.py
bungiesearch/management/commands/search_index.py
bungiesearch/management/commands/__init__.py
bungiesearch/management/commands/rebuild_index.py
bungiesearch/management/commands/clear_index.py
bungiesearch-1.3.0.dist-info/METADATA
bungiesearch-1.3.0.dist-info/top_level.txt
bungiesearch-1.3.0.dist-info/metadata.json
bungiesearch-1.3.0.dist-info/RECORD
bungiesearch-1.3.0.dist-info/WHEEL
bungiesearch-1.3.0.dist-info/DESCRIPTION.rst
bungiesearch-1.3.0.dist-info/dependency_links.txt
tests/__init__.py
tests/manage.py
tests/settings.py
tests/core/bungie_signal.py
tests/core/search_aliases.py
tests/core/__init__.py
tests/core/test_bungiesearch.py
tests/core/search_indices.py
tests/core/search_indices_bis.py
tests/core/models.py
tests/core/analysis.py
