Metadata-Version: 2.0
Name: bungiesearch
Version: 1.3.0
Summary: A Django elasticsearch wrapper and helper using elasticsearch-dsl-py high level library.
Home-page: https://github.com/ChristopherRabotin/bungiesearch
Author: Christopher Rabotin
Author-email: christopher.rabotin@gmail.com
License: BSD-3
Keywords: elasticsearch haystack django bungiesearch
Platform: UNKNOWN
Classifier: Development Status :: 5 - Production/Stable
Classifier: Intended Audience :: Developers
Classifier: License :: OSI Approved :: BSD License
Classifier: Operating System :: OS Independent
Classifier: Programming Language :: Python :: 2
Classifier: Framework :: Django
Requires-Dist: django (>=1.6)
Requires-Dist: elasticsearch-dsl (>=0.0.4)
Requires-Dist: elasticsearch (>=1.0.0,<=2.1.0python-dateutil)
Requires-Dist: six
